frankfurtermcp/__init__.py
frankfurtermcp/common.py
frankfurtermcp/middleware.py
frankfurtermcp/mixin.py
frankfurtermcp/model.py
frankfurtermcp/server.py
frankfurtermcp-0.4.3.dist-info/METADATA
frankfurtermcp-0.4.3.dist-info/WHEEL
frankfurtermcp-0.4.3.dist-info/entry_points.txt
frankfurtermcp-0.4.3.dist-info/licenses/LICENSE
frankfurtermcp-0.4.3.dist-info/RECORD
