Metadata-Version: 2.4
Name: frankfurtermcp
Version: 0.4.3
Summary: A MCP server for currency exchange rates and currency conversion using the Frankfurter API.
Project-URL: Repository, https://github.com/anirbanbasu/frankfurtermcp
Project-URL: Issues, https://github.com/anirbanbasu/frankfurtermcp/issues
Project-URL: Download, https://pypi.org/project/frankfurtermcp/
Author-email: Anirban Basu <anirbanbasu@users.noreply.github.com>
License-Expression: MIT
License-File: LICENSE
Keywords: currency-converter,currency-exchange-rates,fastmcp,finance,frankfurter-api,mcp,mcp-composition,mcp-server,model-context-protocol,model-context-protocol-server
Classifier: Development Status :: 5 - Production/Stable
Classifier: Intended Audience :: Developers
Classifier: Intended Audience :: End Users/Desktop
Classifier: Intended Audience :: Financial and Insurance Industry
Classifier: License :: OSI Approved :: MIT License
Classifier: Programming Language :: Python :: 3
Classifier: Programming Language :: Python :: 3.12
Requires-Python: <3.14,>=3.12
Requires-Dist: cachetools>=6.2.1
Requires-Dist: environs>=14.3.0
Requires-Dist: fastmcp>=2.13.1
Requires-Dist: pycountry>=24.6.1
Requires-Dist: pydantic-extra-types>=2.10.5
Requires-Dist: types-cachetools>=6.2.0.20250827
